colton/__about__.py
colton/__init__.py
colton-0.0.1.dist-info/METADATA
colton-0.0.1.dist-info/WHEEL
colton-0.0.1.dist-info/licenses/LICENSE.txt
colton-0.0.1.dist-info/RECORD
